postprocessor/argsParser.py
postprocessor/main.py
postprocessor/converter/RobodkUR2Pulse.py
postprocessor/converter/__init__.py
postprocessor/converter/linalg.py
postprocessor/converter/programParser.py
processedPrograms/path.py
URToPulseConverter-0.2.5.dist-info/LICENSE
URToPulseConverter-0.2.5.dist-info/METADATA
URToPulseConverter-0.2.5.dist-info/WHEEL
URToPulseConverter-0.2.5.dist-info/entry_points.txt
URToPulseConverter-0.2.5.dist-info/top_level.txt
URToPulseConverter-0.2.5.dist-info/RECORD
