Metadata-Version: 2.1
Name: URToPulseConverter
Version: 0.2.5
Summary: UR Robot script -> 'Rozum Robotics' Pulse Robots code converter 
Home-page: UNKNOWN
Author: Ostapets Vladislav
Author-email: vlad12344444@gmail.com
License: UNKNOWN
Platform: UNKNOWN
Classifier: Programming Language :: Python :: 3.8
Classifier: License :: OSI Approved :: MIT License
Requires-Python: >=3.6
Requires-Dist: numpy (==1.18.0)
